src/uart.v
module uart
#(
    parameter DELAY_FRAMES = 234 // 27,000,000 (27Mhz) / 115200 Baud rate
)
(
    input  wire       clk,
    input  wire       uart_rx,
    output wire       uart_tx,
    input  wire       btn1,
    output reg  [5:0] led,
    output reg        byteReady,
    output reg        msgReady,
    output reg  [7:0] dataIn

);
    localparam HALF_DELAY_WAIT = (DELAY_FRAMES / 2);
    localparam MEMORY_LENGTH = 11;

    reg [7:0] testMemory [MEMORY_LENGTH-1:0];

    initial begin
        testMemory[0] = "I";
        testMemory[1] = "O";
        testMemory[2] = "T";
        testMemory[3] = ".";
        testMemory[4] = "C";
        testMemory[5] = "K";
        testMemory[6] = ".";
        testMemory[7] = "U";
        testMemory[8] = "A";
        testMemory[9] = 8'h0D;
        testMemory[10] = 8'h0A; 
    end

    localparam RX_STATE_IDLE = 0;
    localparam RX_STATE_START_BIT = 1;
    localparam RX_STATE_READ_WAIT = 2;
    localparam RX_STATE_READ = 3;
    localparam RX_STATE_STOP_BIT = 4;

    localparam MSG_STATE_IDLE = 0;
    localparam MSG_STATE_RECEIVING = 1;

    localparam TX_STATE_IDLE = 0;
    localparam TX_STATE_START_BIT = 1;
    localparam TX_STATE_WRITE = 2;
    localparam TX_STATE_STOP_BIT = 3;
    localparam TX_STATE_DEBOUNCE = 4;

    reg [3:0] rxState = 0;
    reg [12:0] rxCounter = 0;
    reg [2:0] rxBitNumber = 0;

    reg [3:0] txState = 0;
    reg [24:0] txCounter = 0;
    reg [7:0] dataOut = 0;
    reg txPinRegister = 1;
    reg [2:0] txBitNumber = 0;
    reg [3:0] txByteCounter = 0;

    assign uart_tx = txPinRegister;

    // Synchronize and debounce btn1 so the FSM only ever sees a clean,
    // stable level (raw button bounce was glitching the FSM mid-transmission).
    localparam BTN_DEBOUNCE_CYCLES = 25'd270000; // ~10ms @ 27MHz

    reg [1:0] btn1Sync = 2'b11;
    reg btn1Clean = 1;
    reg [24:0] btn1DebounceCounter = 0;

    always @(posedge clk) begin
        btn1Sync <= {btn1Sync[0], btn1};

        if (btn1Sync[1] != btn1Clean) begin
            if (btn1DebounceCounter == BTN_DEBOUNCE_CYCLES) begin
                btn1Clean <= btn1Sync[1];
                btn1DebounceCounter <= 0;
            end else
                btn1DebounceCounter <= btn1DebounceCounter + 1;
        end else
            btn1DebounceCounter <= 0;
    end

    always @(posedge clk) begin
        case (rxState)
            RX_STATE_IDLE: begin
                if (uart_rx == 0) begin
                    rxState <= RX_STATE_START_BIT;
                    rxCounter <= 1;
                    rxBitNumber <= 0;
                    byteReady <= 0;
                end
            end 
            RX_STATE_START_BIT: begin
                if (rxCounter == HALF_DELAY_WAIT) begin
                    rxState <= RX_STATE_READ_WAIT;
                    rxCounter <= 1;
                end else 
                    rxCounter <= rxCounter + 1;
            end
            RX_STATE_READ_WAIT: begin
                rxCounter <= rxCounter + 1;
                if ((rxCounter + 1) == DELAY_FRAMES) begin
                    rxState <= RX_STATE_READ;
                end
            end
            RX_STATE_READ: begin
                rxCounter <= 1;
                dataIn <= {uart_rx, dataIn[7:1]};
                rxBitNumber <= rxBitNumber + 1;
                if (rxBitNumber == 3'b111)
                    rxState <= RX_STATE_STOP_BIT;
                else
                    rxState <= RX_STATE_READ_WAIT;
            end
            RX_STATE_STOP_BIT: begin
                rxCounter <= rxCounter + 1;
                if ((rxCounter + 1) == DELAY_FRAMES) begin
                    rxState <= RX_STATE_IDLE;
                    rxCounter <= 0;
                    byteReady <= 1;
                end
            end
        endcase
    end

    reg [7:0] msgCounter = 0;
    reg [1:0] msgState = 0;

    always @(posedge clk) begin
        case(msgState)
            MSG_STATE_IDLE: begin
                if (byteReady) begin
                    msgState <= MSG_STATE_RECEIVING;
                    msgCounter <= 0;
                    msgReady <= 0;
                end
            end
            MSG_STATE_RECEIVING: begin
                if (byteReady) begin
                    msgCounter <= 0;
                    msgReady <= 0;
                end else if (msgCounter == HALF_DELAY_WAIT * 6) begin
                    msgState <= MSG_STATE_IDLE;
                    msgReady <= 1;
                end else begin
                    msgCounter <= msgCounter + 1;
                end
            end
        endcase
    end

    always @(posedge clk) begin
        if (byteReady) begin
            led <= ~dataIn[5:0];
        end
    end

    always @(posedge clk) begin
        case (txState)
            TX_STATE_IDLE: begin
                if (btn1Clean == 0) begin
                    txState <= TX_STATE_START_BIT;
                    txCounter <= 0;
                    txByteCounter <= 0;
                end
                else begin
                    txPinRegister <= 1;
                end
            end 
            TX_STATE_START_BIT: begin
                txPinRegister <= 0;
                if ((txCounter + 1) == DELAY_FRAMES) begin
                    txState <= TX_STATE_WRITE;
                    dataOut <= testMemory[txByteCounter];
                    txBitNumber <= 0;
                    txCounter <= 0;
                end else 
                    txCounter <= txCounter + 1;
            end
            TX_STATE_WRITE: begin
                txPinRegister <= dataOut[txBitNumber];
                if ((txCounter + 1) == DELAY_FRAMES) begin
                    if (txBitNumber == 3'b111) begin
                        txState <= TX_STATE_STOP_BIT;
                    end else begin
                        txState <= TX_STATE_WRITE;
                        txBitNumber <= txBitNumber + 1;
                    end
                    txCounter <= 0;
                end else 
                    txCounter <= txCounter + 1;
            end
            TX_STATE_STOP_BIT: begin
                txPinRegister <= 1;
                if ((txCounter + 1) == DELAY_FRAMES) begin
                    if (txByteCounter == MEMORY_LENGTH - 1) begin
                        txState <= TX_STATE_DEBOUNCE;
                    end else begin
                        txByteCounter <= txByteCounter + 1;
                        txState <= TX_STATE_START_BIT;
                    end
                    txCounter <= 0;
                end else 
                    txCounter <= txCounter + 1;
            end
            TX_STATE_DEBOUNCE: begin
                if (btn1Clean == 1)
                    txState <= TX_STATE_IDLE;       // button released (already debounced)
            end
        endcase      
    end

endmodule

src/uart_tb.v
module test();
    reg clk = 0;
    reg uart_rx = 1;
    wire uart_tx;
    reg btn1 = 1;
    wire [5:0] led;

    uart #(8'd8) u(
        clk,
        uart_rx,
        uart_tx,
        btn1,
        led
    );

    always
        #1  clk = ~clk;

    initial begin
        $display("Starting UART RX");
        $monitor("LED Value %b", led);
        #10 uart_rx=0;
        #16 uart_rx=1;
        #16 uart_rx=0;
        #16 uart_rx=0;
        #16 uart_rx=0;
        #16 uart_rx=0;
        #16 uart_rx=1;
        #16 uart_rx=1;
        #16 uart_rx=0;
        #16 uart_rx=1;
        #4 btn1=0;
        #4 btn1=1;
        #1000 $finish;
    end

    initial begin
        $dumpfile("uart.vcd");
        $dumpvars(0,test);
    end
endmodule

uart.vcd
$date
	Sat Jun 13 10:42:12 2026
$end
$version
	Icarus Verilog
$end
$timescale
	1s
$end
$scope module test $end
$var wire 1 ! uart_tx $end
$var wire 6 " led [5:0] $end
$var reg 1 # btn1 $end
$var reg 1 $ clk $end
$var reg 1 % uart_rx $end
$scope module u $end
$var wire 1 # btn1 $end
$var wire 1 $ clk $end
$var wire 1 % uart_rx $end
$var wire 1 ! uart_tx $end
$var parameter 8 & DELAY_FRAMES $end
$var parameter 32 ' HALF_DELAY_WAIT $end
$var parameter 32 ( RX_STATE_IDLE $end
$var parameter 32 ) RX_STATE_READ $end
$var parameter 32 * RX_STATE_READ_WAIT $end
$var parameter 32 + RX_STATE_START_BIT $end
$var parameter 32 , RX_STATE_STOP_BIT $end
$var reg 1 - byteReady $end
$var reg 8 . dataIn [7:0] $end
$var reg 6 / led [5:0] $end
$var reg 3 0 rxBitNumber [2:0] $end
$var reg 13 1 rxCounter [12:0] $end
$var reg 4 2 rxState [3:0] $end
$upscope $end
$upscope $end
$enddefinitions $end
$comment Show the parameter values. $end
$dumpall
b101 ,
b1 +
b10 *
b11 )
b0 (
b100 '
b1000 &
$end
#0
$dumpvars
b0 2
b0 1
b0 0
bx /
b0 .
0-
1%
0$
1#
bx "
z!
$end
#1
1$
#2
0$
#3
1$
#4
0$
#5
1$
#6
0$
#7
1$
#8
0$
#9
1$
#10
0$
0%
#11
b1 1
b1 2
1$
#12
0$
#13
b10 1
1$
#14
0$
#15
b11 1
1$
#16
0$
#17
b100 1
1$
#18
0$
#19
b1 1
b10 2
1$
#20
0$
#21
b10 1
1$
#22
0$
#23
b11 1
1$
#24
0$
#25
b100 1
1$
#26
0$
1%
#27
b101 1
1$
#28
0$
#29
b110 1
1$
#30
0$
#31
b111 1
1$
#32
0$
#33
b11 2
b1000 1
1$
#34
0$
#35
b10 2
b1 0
b10000000 .
b1 1
1$
#36
0$
#37
b10 1
1$
#38
0$
#39
b11 1
1$
#40
0$
#41
b100 1
1$
#42
0$
0%
#43
b101 1
1$
#44
0$
#45
b110 1
1$
#46
0$
#47
b111 1
1$
#48
0$
#49
b11 2
b1000 1
1$
#50
0$
#51
b10 2
b10 0
b1000000 .
b1 1
1$
#52
0$
#53
b10 1
1$
#54
0$
#55
b11 1
1$
#56
0$
#57
b100 1
1$
#58
0$
#59
b101 1
1$
#60
0$
#61
b110 1
1$
#62
0$
#63
b111 1
1$
#64
0$
#65
b11 2
b1000 1
1$
#66
0$
#67
b10 2
b11 0
b100000 .
b1 1
1$
#68
0$
#69
b10 1
1$
#70
0$
#71
b11 1
1$
#72
0$
#73
b100 1
1$
#74
0$
#75
b101 1
1$
#76
0$
#77
b110 1
1$
#78
0$
#79
b111 1
1$
#80
0$
#81
b11 2
b1000 1
1$
#82
0$
#83
b10 2
b100 0
b10000 .
b1 1
1$
#84
0$
#85
b10 1
1$
#86
0$
#87
b11 1
1$
#88
0$
#89
b100 1
1$
#90
0$
#91
b101 1
1$
#92
0$
#93
b110 1
1$
#94
0$
#95
b111 1
1$
#96
0$
#97
b11 2
b1000 1
1$
#98
0$
#99
b10 2
b101 0
b1000 .
b1 1
1$
#100
0$
#101
b10 1
1$
#102
0$
#103
b11 1
1$
#104
0$
#105
b100 1
1$
#106
0$
1%
#107
b101 1
1$
#108
0$
#109
b110 1
1$
#110
0$
#111
b111 1
1$
#112
0$
#113
b11 2
b1000 1
1$
#114
0$
#115
b10 2
b110 0
b10000100 .
b1 1
1$
#116
0$
#117
b10 1
1$
#118
0$
#119
b11 1
1$
#120
0$
#121
b100 1
1$
#122
0$
#123
b101 1
1$
#124
0$
#125
b110 1
1$
#126
0$
#127
b111 1
1$
#128
0$
#129
b11 2
b1000 1
1$
#130
0$
#131
b10 2
b111 0
b11000010 .
b1 1
1$
#132
0$
#133
b10 1
1$
#134
0$
#135
b11 1
1$
#136
0$
#137
b100 1
1$
#138
0$
0%
#139
b101 1
1$
#140
0$
#141
b110 1
1$
#142
0$
#143
b111 1
1$
#144
0$
#145
b11 2
b1000 1
1$
#146
0$
#147
b101 2
b0 0
b1100001 .
b1 1
1$
#148
0$
#149
b10 1
1$
#150
0$
#151
b11 1
1$
#152
0$
#153
b100 1
1$
#154
0$
1%
#155
b101 1
1$
#156
0$
#157
b110 1
1$
#158
0$
0#
#159
b111 1
1$
#160
0$
#161
1-
b0 2
b0 1
1$
#162
0$
1#
#163
b11110 "
b11110 /
1$
